[
{
    "id": 30761,
    "cc": "CS610",
    "qn": "3",
    "dt": "01 July 2026",
    "qt": "The identifier that is used for data transfer in the virtual circuit network is called _______.",
    "op": [
        "Global address",
        "Virtual circuit identifier",
        "Network identifier",
        "IP identifier"
    ],
    "created_at": "2026-06-30T19:01:26.96638+00:00"
},
{
    "id": 30771,
    "cc": "CS610",
    "qn": "3",
    "dt": "01 July 2026",
    "qt": "Dotted decimal notation is a syntactic form the IP software uses to express ________ binary values when interacting with humans.",
    "op": [
        "8-bit",
        "32-bit",
        "64-bit",
        "16-bit"
    ],
    "created_at": "2026-06-30T19:01:43.852306+00:00"
},
{
    "id": 30783,
    "cc": "CS610",
    "qn": "3",
    "dt": "01 July 2026",
    "qt": "Asynchronous transfer mode (ATM) is designed to work on fiber but can be used with______________.",
    "op": [
        "wireless",
        "Wifi",
        "Bluetooth",
        "Twisted pair"
    ],
    "created_at": "2026-06-30T19:02:00.034516+00:00"
},
{
    "id": 30797,
    "cc": "CS610",
    "qn": "3",
    "dt": "01 July 2026",
    "qt": "CBR stands for__________.",
    "op": [
        "Constant Bit Rate",
        "Constant Borrow Rate",
        "Connection break Recovery",
        "Constant Byte Rate"
    ],
    "created_at": "2026-06-30T19:02:16.128133+00:00"
},
{
    "id": 30811,
    "cc": "CS610",
    "qn": "3",
    "dt": "01 July 2026",
    "qt": "_______ protocols of TCP/IP layering model specify how to ensure reliable transfer.",
    "op": [
        "Internet Layer",
        "Transport Layer",
        "Network Interface Layer",
        "Physical Layer"
    ],
    "created_at": "2026-06-30T19:02:33.956656+00:00"
},
{
    "id": 30817,
    "cc": "CS610",
    "qn": "3",
    "dt": "01 July 2026",
    "qt": "________________ can’t be guaranteed with variable length packets as easily as it can with fixed length cells.",
    "op": [
        "Errors",
        "None of the given",
        "Quality of Service",
        "Noise"
    ],
    "created_at": "2026-06-30T19:02:46.162646+00:00"
},
{
    "id": 30825,
    "cc": "CS610",
    "qn": "3",
    "dt": "01 July 2026",
    "qt": "A network with ________jitter takes more time to deliver some packets than others.",
    "op": [
        "Moderate",
        "Zero",
        "Low",
        "High"
    ],
    "created_at": "2026-06-30T19:02:59.235483+00:00"
},
{
    "id": 30834,
    "cc": "CS610",
    "qn": "3",
    "dt": "01 July 2026",
    "qt": "_____________ is used for compressed audio and video, where the data rate depends on the level of compression that can be achieved.",
    "op": [
        "Stable Bit Rate",
        "Constant Bit Rate",
        "Variable Bit Rate",
        "Available Bit Rate"
    ],
    "created_at": "2026-06-30T19:03:14.630587+00:00"
},
{
    "id": 30846,
    "cc": "CS610",
    "qn": "3",
    "dt": "01 July 2026",
    "qt": "VBR stands for…………….",
    "op": [
        "Virtual Byte Rate",
        "Variable Bit Rate",
        "Variable Byte Redundancy",
        "Virtual Bit Rate"
    ],
    "created_at": "2026-06-30T19:03:33.08869+00:00"
},
{
    "id": 30921,
    "cc": "CS610",
    "qn": "3",
    "dt": "01 July 2026",
    "qt": "PVC stands for ______________________.",
    "op": [
        "Permanent virtual circuit",
        "Private virtual circuit",
        "Public virtual circuit",
        "Plastic virtual circuit"
    ],
    "created_at": "2026-06-30T19:06:08.710927+00:00"
},
{
    "id": 30931,
    "cc": "CS610",
    "qn": "3",
    "dt": "01 July 2026",
    "qt": "The IP class scheme does not divide the ________ address space into equal size class and the classes do not contain the same number of networks.",
    "op": [
        "16-bit",
        "48-bit",
        "64-bit",
        "32-bit"
    ],
    "created_at": "2026-06-30T19:06:40.586774+00:00"
},
{
    "id": 30939,
    "cc": "CS610",
    "qn": "3",
    "dt": "01 July 2026",
    "qt": "Computer sends a connection request to the ___________to which it is attached while establishing a switched virtual circuit.",
    "op": [
        "Virtual circuit",
        "Bridge",
        "VPI",
        "Switch"
    ],
    "created_at": "2026-06-30T19:06:54.969737+00:00"
},
{
    "id": 30952,
    "cc": "CS610",
    "qn": "3",
    "dt": "01 July 2026",
    "qt": "Dotted decimal represents each octet in ________ and uses a dot to separate octets.",
    "op": [
        "hexadecimal",
        "decimal",
        "Octal",
        "binary"
    ],
    "created_at": "2026-06-30T19:07:13.674123+00:00"
},
{
    "id": 30967,
    "cc": "CS610",
    "qn": "3",
    "dt": "01 July 2026",
    "qt": "__________ Networks are sometimes called Intranet.",
    "op": [
        "WAN",
        "Public",
        "Private",
        "Virtual"
    ],
    "created_at": "2026-06-30T19:07:44.262858+00:00"
},
{
    "id": 30972,
    "cc": "CS610",
    "qn": "3",
    "dt": "01 July 2026",
    "qt": "A typical port on an ATM switch operates at __________ or higher.",
    "op": [
        "OC-2 speed (155Gbps)",
        "OC-2 speed (1000Mbps)",
        "OC-3 speed (100Gbps)",
        "OC-3 speed (155Mbps)"
    ],
    "created_at": "2026-06-30T19:07:55.082046+00:00"
},
{
    "id": 30975,
    "cc": "CS610",
    "qn": "3",
    "dt": "01 July 2026",
    "qt": "In the IP address __________ identifies an individual computer on the network.",
    "op": [
        "Demux",
        "Mux",
        "Prefix",
        "Suffix"
    ],
    "created_at": "2026-06-30T19:08:02.143207+00:00"
},
{
    "id": 30979,
    "cc": "CS610",
    "qn": "3",
    "dt": "01 July 2026",
    "qt": "________ of TCP/IP Protocol Suit specifies the format of packets sent across Internet as well as the mechanisms used to forward packets.",
    "op": [
        "Data Link Layer",
        "Transport Layer",
        "Internet Layer",
        "Physical Layer"
    ],
    "created_at": "2026-06-30T19:08:10.34718+00:00"
},
{
    "id": 30984,
    "cc": "CS610",
    "qn": "3",
    "dt": "01 July 2026",
    "qt": "All of the given options are the types of delay except___________.",
    "op": [
        "Throughput",
        "Propagation",
        "Access",
        "Queuing"
    ],
    "created_at": "2026-06-30T19:08:20.209463+00:00"
},
{
    "id": 30989,
    "cc": "CS610",
    "qn": "3",
    "dt": "01 July 2026",
    "qt": "Internet protocol (IP) address version 4 is comprised of ______ bits.",
    "op": [
        "48",
        "32",
        "24",
        "128"
    ],
    "created_at": "2026-06-30T19:08:23.62979+00:00"
},
{
    "id": 30992,
    "cc": "CS610",
    "qn": "3",
    "dt": "01 July 2026",
    "qt": "As the Internet grew, the original Classful addressing scheme became a limitation. The IP address space was being exhausted because all networks had to choose one of ________ possible sizes.",
    "op": [
        "five",
        "two",
        "three",
        "four"
    ],
    "created_at": "2026-06-30T19:08:29.909068+00:00"
},
{
    "id": 30998,
    "cc": "CS610",
    "qn": "3",
    "dt": "01 July 2026",
    "qt": "Which types of VPNs are used for corporate connectivity across companies residing in different geographical locations?",
    "op": [
        "Site-to-site VPNs",
        "Remote access VPNs",
        "Peer-to-Peer VPNs",
        "Country-to-country VPNs"
    ],
    "created_at": "2026-06-30T19:08:36.259594+00:00"
},
{
    "id": 30999,
    "cc": "CS610",
    "qn": "3",
    "dt": "01 July 2026",
    "qt": "__________is the rate at which data can be sent through the network.",
    "op": [
        "Switching delay",
        "Propagation delay",
        "Access delay",
        "Throughput"
    ],
    "created_at": "2026-06-30T19:08:43.004746+00:00"
},
{
    "id": 31002,
    "cc": "CS610",
    "qn": "3",
    "dt": "01 July 2026",
    "qt": "__________ masks your IP address.",
    "op": [
        "Firewall",
        "VPN",
        "Antivirus",
        "Incognito mode"
    ],
    "created_at": "2026-06-30T19:08:49.427364+00:00"
},
{
    "id": 31006,
    "cc": "CS610",
    "qn": "3",
    "dt": "01 July 2026",
    "qt": "TCP/IP defines the term__________ to refer any computer system that connects to a network and runs applications for users.",
    "op": [
        "Router",
        "Bridge",
        "Switch",
        "Host computer"
    ],
    "created_at": "2026-06-30T19:08:57.504105+00:00"
},
{
    "id": 31049,
    "cc": "CS610",
    "qn": "3",
    "dt": "01 July 2026",
    "qt": "ABR stands for…………….",
    "op": [
        "Asynchronous Bit Redundancy",
        "Available Bit Rate",
        "Asynchronous Bit Rate",
        "Asynchronous Byte Recovery"
    ],
    "created_at": "2026-06-30T19:10:21.489301+00:00"
},
{
    "id": 31052,
    "cc": "CS610",
    "qn": "3",
    "dt": "01 July 2026",
    "qt": "________ of TCP/IP protocol suit defines the basic characteristics of network hardware.",
    "op": [
        "Transport Layer",
        "Physical Layer",
        "Data Link Layer",
        "Internet Layer"
    ],
    "created_at": "2026-06-30T19:10:35.975798+00:00"
},
{
    "id": 31061,
    "cc": "CS610",
    "qn": "3",
    "dt": "01 July 2026",
    "qt": "Handling variable length packets leads to memory _____________.",
    "op": [
        "Allocation",
        "Location",
        "Fragmentation",
        "Management"
    ],
    "created_at": "2026-06-30T19:10:56.316772+00:00"
},
{
    "id": 31073,
    "cc": "CS610",
    "qn": "3",
    "dt": "01 July 2026",
    "qt": "Public networks are _________________.",
    "op": [
        "Limited in boundary",
        "Intranet",
        "Flexible",
        "More secure than LAN"
    ],
    "created_at": "2026-06-30T19:11:26.829483+00:00"
},
{
    "id": 31100,
    "cc": "CS610",
    "qn": "3",
    "dt": "01 July 2026",
    "qt": "The length of time required to send a variable length packet is _____________",
    "op": [
        "Fix",
        "5 seconds",
        "Variable",
        "Constant"
    ],
    "created_at": "2026-06-30T19:12:20.92094+00:00"
},
{
    "id": 31115,
    "cc": "CS610",
    "qn": "3",
    "dt": "01 July 2026",
    "qt": "________ protocols of TCP/IP layering model specify how to organize data into frame and how a computer transmits frames over a network.",
    "op": [
        "Transport Layer",
        "Network Interface Layer",
        "Session",
        "Internet Layer"
    ],
    "created_at": "2026-06-30T19:12:44.359001+00:00"
},
{
    "id": 31152,
    "cc": "CS610",
    "qn": "3",
    "dt": "01 July 2026",
    "qt": "Inside a computer, each address mask is stored as a ____-bit value.",
    "op": [
        "16",
        "64",
        "32",
        "48"
    ],
    "created_at": "2026-06-30T19:13:59.903247+00:00"
},
{
    "id": 31519,
    "cc": "CS610",
    "qn": "3",
    "dt": "01 July 2026",
    "qt": "In the IP address ___________ identifies the physical network to which the computer is attached.",
    "op": [
        "Demux",
        "Prefix",
        "Suffix",
        "Mux"
    ],
    "created_at": "2026-06-30T19:28:01.278566+00:00"
},
{
    "id": 32089,
    "cc": "CS610",
    "qn": "3",
    "dt": "01 July 2026",
    "qt": "VPNs connections are sometimes called __________.",
    "op": [
        "Tunnels",
        "Routing",
        "Public network",
        "Open networking"
    ],
    "created_at": "2026-06-30T19:57:18.278677+00:00"
},
{
    "id": 43001,
    "cc": "CS610",
    "qn": "3",
    "dt": "01 July 2026",
    "qt": "_____________ is used for compressed audio and video, where the data rate depends on the level of compression that can be achieved.",
    "op": [
        "Stable Bit Rate",
        "Constant Bit Rate",
        "Variable Bit Rate",
        "Available Bit Rate"
    ],
    "created_at": "2026-07-01T06:54:01.29+00:00"
},
{
    "id": 43002,
    "cc": "CS610",
    "qn": "3",
    "dt": "01 July 2026",
    "qt": "__________ masks your IP address.",
    "op": [
        "VPN",
        "Incognito mode",
        "Antivirus",
        "Firewall"
    ],
    "created_at": "2026-07-01T06:54:11.896469+00:00"
},
{
    "id": 43003,
    "cc": "CS610",
    "qn": "3",
    "dt": "01 July 2026",
    "qt": "VBR stands for…………….",
    "op": [
        "Variable Bit Rate",
        "Virtual Byte Rate",
        "Variable Byte Redundancy",
        "Virtual Bit Rate"
    ],
    "created_at": "2026-07-01T06:54:23.946314+00:00"
},
{
    "id": 43004,
    "cc": "CS610",
    "qn": "3",
    "dt": "01 July 2026",
    "qt": "As the Internet grew, the original Classful addressing scheme became a limitation. The IP address space was being exhausted because all networks had to choose one of ________ possible sizes.",
    "op": [
        "five",
        "two",
        "four",
        "three"
    ],
    "created_at": "2026-07-01T06:54:35.877388+00:00"
},
{
    "id": 43005,
    "cc": "CS610",
    "qn": "3",
    "dt": "01 July 2026",
    "qt": "Handling variable length packets leads to memory _____________.",
    "op": [
        "Fragmentation",
        "Location",
        "Management",
        "Allocation"
    ],
    "created_at": "2026-07-01T06:54:44.496505+00:00"
},
{
    "id": 43006,
    "cc": "CS610",
    "qn": "3",
    "dt": "01 July 2026",
    "qt": "The identifier that is used for data transfer in the virtual circuit network is called _______.",
    "op": [
        "Network identifier",
        "IP identifier",
        "Global address",
        "Virtual circuit identifier"
    ],
    "created_at": "2026-07-01T06:54:52.898391+00:00"
},
{
    "id": 43007,
    "cc": "CS610",
    "qn": "3",
    "dt": "01 July 2026",
    "qt": "________ of TCP/IP protocol suit defines the basic characteristics of network hardware.",
    "op": [
        "Data Link Layer",
        "Internet Layer",
        "Physical Layer",
        "Transport Layer"
    ],
    "created_at": "2026-07-01T06:55:01.755596+00:00"
},
{
    "id": 43008,
    "cc": "CS610",
    "qn": "3",
    "dt": "01 July 2026",
    "qt": "In the IP address ___________ identifies the physical network to which the computer is attached.",
    "op": [
        "Prefix",
        "Mux",
        "Demux",
        "Suffix"
    ],
    "created_at": "2026-07-01T06:55:13.215499+00:00"
},
{
    "id": 43009,
    "cc": "CS610",
    "qn": "3",
    "dt": "01 July 2026",
    "qt": "The length of time required to send a variable length packet is _____________",
    "op": [
        "Constant",
        "Fix",
        "5 seconds",
        "Variable"
    ],
    "created_at": "2026-07-01T06:55:21.233928+00:00"
},
{
    "id": 43010,
    "cc": "CS610",
    "qn": "3",
    "dt": "01 July 2026",
    "qt": "Public networks are _________________.",
    "op": [
        "More secure than LAN",
        "Intranet",
        "Flexible",
        "Limited in boundary"
    ],
    "created_at": "2026-07-01T06:55:29.204437+00:00"
},
{
    "id": 57130,
    "cc": "CS610",
    "qn": "4",
    "dt": "08 July 2026",
    "qt": "_________ uses window mechanism to control the flow of data.",
    "op": [
        "UDP",
        "TCP",
        "IP",
        "none of the given"
    ],
    "created_at": "2026-07-07T19:01:48.936069+00:00"
},
{
    "id": 57131,
    "cc": "CS610",
    "qn": "4",
    "dt": "08 July 2026",
    "qt": "__________ sends ICMP echo messages with increasing TTL.",
    "op": [
        "Ping",
        "Tracert",
        "Trace route",
        "none of the given"
    ],
    "created_at": "2026-07-07T19:01:58.925438+00:00"
},
{
    "id": 57133,
    "cc": "CS610",
    "qn": "4",
    "dt": "08 July 2026",
    "qt": "The Network Layer Protocol ICMP stands for____________",
    "op": [
        "Instant Control Message Protocol",
        "Internet Control Message Protocol",
        "Initial Control Message Protocol",
        "None of the given"
    ],
    "created_at": "2026-07-07T19:02:10.053342+00:00"
},
{
    "id": 57135,
    "cc": "CS610",
    "qn": "4",
    "dt": "08 July 2026",
    "qt": "_____ Protocol provides error reporting mechanism.",
    "op": [
        "SNMP",
        "IGMP",
        "none of the given",
        "ICMP"
    ],
    "created_at": "2026-07-07T19:02:21.468676+00:00"
},
{
    "id": 57138,
    "cc": "CS610",
    "qn": "4",
    "dt": "08 July 2026",
    "qt": "Routers use _______ to forward datagrams along prearranged path.",
    "op": [
        "Traffic class",
        "Destination address",
        "none of the given",
        "Flow label"
    ],
    "created_at": "2026-07-07T19:02:31.400628+00:00"
},
{
    "id": 57141,
    "cc": "CS610",
    "qn": "4",
    "dt": "08 July 2026",
    "qt": "_______ protocol uses three way handshake to begin a connection.",
    "op": [
        "UDP",
        "IP",
        "none of the given",
        "TCP"
    ],
    "created_at": "2026-07-07T19:02:41.1096+00:00"
},
{
    "id": 57145,
    "cc": "CS610",
    "qn": "4",
    "dt": "08 July 2026",
    "qt": "Class A mask is 255.0.0.0 which is used for ______",
    "op": [
        "Unicasting",
        "Subnetting",
        "All of the given",
        "Multicasting"
    ],
    "created_at": "2026-07-07T19:02:53.761466+00:00"
},
{
    "id": 57149,
    "cc": "CS610",
    "qn": "4",
    "dt": "08 July 2026",
    "qt": "______________field tells the receiver how to order fragments within a given datagram.",
    "op": [
        "FLAGS",
        "FRAGMENT OFFSET",
        "IDENTIFICATION",
        "None of the given"
    ],
    "created_at": "2026-07-07T19:03:03.848963+00:00"
},
{
    "id": 57152,
    "cc": "CS610",
    "qn": "4",
    "dt": "08 July 2026",
    "qt": "UDP datagram format is _______ bits.",
    "op": [
        "32",
        "8",
        "16",
        "64"
    ],
    "created_at": "2026-07-07T19:03:14.738773+00:00"
},
{
    "id": 57164,
    "cc": "CS610",
    "qn": "4",
    "dt": "08 July 2026",
    "qt": "IPv6 ______________ is responsible for fragmentation. Routers simply drop datagram’s larger than network",
    "op": [
        "Medium",
        "Destination",
        "Intermediate routers",
        "Source"
    ],
    "created_at": "2026-07-07T19:04:10.235778+00:00"
},
{
    "id": 57167,
    "cc": "CS610",
    "qn": "4",
    "dt": "08 July 2026",
    "qt": "A datagram cannot be larger than ________ of a network over which it is sent.",
    "op": [
        "IP header",
        "None of the given",
        "Size",
        "MTU"
    ],
    "created_at": "2026-07-07T19:04:26.94911+00:00"
},
{
    "id": 57170,
    "cc": "CS610",
    "qn": "4",
    "dt": "08 July 2026",
    "qt": "System rebooting is one of the major problems in the reliable delivery",
    "op": [
        "False",
        "True"
    ],
    "created_at": "2026-07-07T19:04:43.949471+00:00"
},
{
    "id": 57176,
    "cc": "CS610",
    "qn": "4",
    "dt": "08 July 2026",
    "qt": "UDP provides connection-oriented service.",
    "op": [
        "False",
        "True"
    ],
    "created_at": "2026-07-07T19:05:00.654043+00:00"
},
{
    "id": 57184,
    "cc": "CS610",
    "qn": "4",
    "dt": "08 July 2026",
    "qt": "The Universal Datagram Protocol is not an end-to-end protocol.",
    "op": [
        "False",
        "True"
    ],
    "created_at": "2026-07-07T19:05:25.424525+00:00"
},
{
    "id": 57192,
    "cc": "CS610",
    "qn": "4",
    "dt": "08 July 2026",
    "qt": "_____ are two standard implementations to improve computational efficiency.",
    "op": [
        "Segmentation and Fragmentation",
        "Queuing and Packetizing",
        "Hashing and Direct indexing",
        "Indexing and Framing"
    ],
    "created_at": "2026-07-07T19:05:37.097284+00:00"
},
{
    "id": 57199,
    "cc": "CS610",
    "qn": "4",
    "dt": "08 July 2026",
    "qt": "Fragmentation when using ICMP for path MTU should be avoided.",
    "op": [
        "False",
        "True"
    ],
    "created_at": "2026-07-07T19:05:48.703349+00:00"
},
{
    "id": 57200,
    "cc": "CS610",
    "qn": "4",
    "dt": "08 July 2026",
    "qt": "_______ Source is responsible for fragmentation.",
    "op": [
        "IPV6",
        "IPV4"
    ],
    "created_at": "2026-07-07T19:05:49.165704+00:00"
},
{
    "id": 57201,
    "cc": "CS610",
    "qn": "4",
    "dt": "08 July 2026",
    "qt": "For _____________, information about forwarding is stored in a routing table, which is initialized at system initialization and must be updated as network topology changes.",
    "op": [
        "Security",
        "Accuracy",
        "Anomalies",
        "Efficiency"
    ],
    "created_at": "2026-07-07T19:05:53.388191+00:00"
},
{
    "id": 57208,
    "cc": "CS610",
    "qn": "4",
    "dt": "08 July 2026",
    "qt": "TCP achieves _________ by retransmission.",
    "op": [
        "Accuracy",
        "Efficiency",
        "none of the given",
        "Reliability"
    ],
    "created_at": "2026-07-07T19:06:09.952654+00:00"
},
{
    "id": 57215,
    "cc": "CS610",
    "qn": "4",
    "dt": "08 July 2026",
    "qt": "Preliminary version of IP was called _________.",
    "op": [
        "IP - New Generation (IPng)",
        "IP - Net Generation (IPng)",
        "None of the given",
        "IP - Next Generation (IPng)"
    ],
    "created_at": "2026-07-07T19:06:26.270777+00:00"
},
{
    "id": 57220,
    "cc": "CS610",
    "qn": "4",
    "dt": "08 July 2026",
    "qt": "There are _______ possibilities to detect the destination using Trace-route",
    "op": [
        "None of the given",
        "2",
        "1",
        "3"
    ],
    "created_at": "2026-07-07T19:06:32.832596+00:00"
},
{
    "id": 57226,
    "cc": "CS610",
    "qn": "4",
    "dt": "08 July 2026",
    "qt": "The protocol address of the next hop must be _____________ to an equivalent hardware address before a packet can be sent.",
    "op": [
        "Segmented",
        "Translated",
        "Decrypted",
        "Encrypted"
    ],
    "created_at": "2026-07-07T19:06:46.600142+00:00"
},
{
    "id": 57228,
    "cc": "CS610",
    "qn": "4",
    "dt": "08 July 2026",
    "qt": "________ is a type of address used for collection of computers with same prefix.",
    "op": [
        "none of the given",
        "unicast",
        "Multicast",
        "Cluster"
    ],
    "created_at": "2026-07-07T19:06:51.427167+00:00"
},
{
    "id": 57239,
    "cc": "CS610",
    "qn": "4",
    "dt": "08 July 2026",
    "qt": "Reliability is not the responsibility of the Transport layer.",
    "op": [
        "False",
        "True"
    ],
    "created_at": "2026-07-07T19:07:17.955666+00:00"
},
{
    "id": 57246,
    "cc": "CS610",
    "qn": "4",
    "dt": "08 July 2026",
    "qt": "A separate ___________ table is used for each physical network.",
    "op": [
        "Checksum",
        "bit-binding",
        "address-binding",
        "CRC"
    ],
    "created_at": "2026-07-07T19:07:40.993613+00:00"
},
{
    "id": 57251,
    "cc": "CS610",
    "qn": "4",
    "dt": "08 July 2026",
    "qt": "HEADER LEN field gives size of extention header.",
    "op": [
        "True",
        "False"
    ],
    "created_at": "2026-07-07T19:08:11.929189+00:00"
},
{
    "id": 57253,
    "cc": "CS610",
    "qn": "4",
    "dt": "08 July 2026",
    "qt": "TCP is a ______ protocol.",
    "op": [
        "None of the given",
        "Multi-Point",
        "Both (a) and (b)",
        "Point-to-Point"
    ],
    "created_at": "2026-07-07T19:08:28.061953+00:00"
},
{
    "id": 57254,
    "cc": "CS610",
    "qn": "4",
    "dt": "08 July 2026",
    "qt": "Header contains all information needed to deliver datagram to the destination computer. But which one of the following is not included:",
    "op": [
        "Destination address",
        "Source address",
        "Rectifier",
        "Other delivery information"
    ],
    "created_at": "2026-07-07T19:08:29.228951+00:00"
},
{
    "id": 57255,
    "cc": "CS610",
    "qn": "4",
    "dt": "08 July 2026",
    "qt": "The Source can configure outgoing datagram’s to avoid _________",
    "op": [
        "Defragmentation",
        "Fragmentation",
        "None of the given",
        "Segmentation"
    ],
    "created_at": "2026-07-07T19:08:33.511879+00:00"
},
{
    "id": 57266,
    "cc": "CS610",
    "qn": "4",
    "dt": "08 July 2026",
    "qt": "________ field is used to identify a specific path through the network",
    "op": [
        "TRAFFIC CLASS",
        "Both a and b",
        "none of the given",
        "FLOW LABEL"
    ],
    "created_at": "2026-07-07T19:08:58.100981+00:00"
},
{
    "id": 57269,
    "cc": "CS610",
    "qn": "4",
    "dt": "08 July 2026",
    "qt": "______ layer Provides reliable delivery of datagram.",
    "op": [
        "Network",
        "Transport",
        "none of the given",
        "Datalink"
    ],
    "created_at": "2026-07-07T19:09:12.536406+00:00"
},
{
    "id": 57272,
    "cc": "CS610",
    "qn": "4",
    "dt": "08 July 2026",
    "qt": "UDP packet is encapsulated in ________ datagram.",
    "op": [
        "None of the given",
        "TCP/IP",
        "TCP",
        "IP"
    ],
    "created_at": "2026-07-07T19:09:20.25405+00:00"
},
{
    "id": 57275,
    "cc": "CS610",
    "qn": "4",
    "dt": "08 July 2026",
    "qt": "TCP provides reliable connection startup.",
    "op": [
        "False",
        "True"
    ],
    "created_at": "2026-07-07T19:09:25.420608+00:00"
},
{
    "id": 57277,
    "cc": "CS610",
    "qn": "4",
    "dt": "08 July 2026",
    "qt": "The maximum segment size of TCP flow control is ___________",
    "op": [
        "1000 octets",
        "none of the given",
        "2000 octets",
        "3000 octets"
    ],
    "created_at": "2026-07-07T19:09:31.609344+00:00"
},
{
    "id": 57288,
    "cc": "CS610",
    "qn": "4",
    "dt": "08 July 2026",
    "qt": "_______ is used for single destination computer.",
    "op": [
        "unicast",
        "Broadcast",
        "Multicast",
        "none of the given"
    ],
    "created_at": "2026-07-07T19:10:02.628107+00:00"
},
{
    "id": 57291,
    "cc": "CS610",
    "qn": "4",
    "dt": "08 July 2026",
    "qt": "Every hardware technology specification includes the definition of the maximum size of the frame data area, which is called the ____________ Transmission Unit.",
    "op": [
        "Least",
        "Maximum",
        "Fragment",
        "Frame"
    ],
    "created_at": "2026-07-07T19:10:10.420633+00:00"
},
{
    "id": 57292,
    "cc": "CS610",
    "qn": "4",
    "dt": "08 July 2026",
    "qt": "_______ is a technique used to Limit datagram size to small MTU of any network",
    "op": [
        "Segmentation",
        "Fragmentation",
        "none of the given",
        "Encapsulation"
    ],
    "created_at": "2026-07-07T19:10:16.38515+00:00"
},
{
    "id": 57299,
    "cc": "CS610",
    "qn": "4",
    "dt": "08 July 2026",
    "qt": "______ provides computer to computer communication.",
    "op": [
        "TCP",
        "ICMP",
        "IGMP",
        "IP"
    ],
    "created_at": "2026-07-07T19:10:33.420827+00:00"
},
{
    "id": 57311,
    "cc": "CS610",
    "qn": "4",
    "dt": "08 July 2026",
    "qt": "UDP uses best-effort delivery service.",
    "op": [
        "True",
        "False"
    ],
    "created_at": "2026-07-07T19:11:08.384954+00:00"
},
{
    "id": 57313,
    "cc": "CS610",
    "qn": "4",
    "dt": "08 July 2026",
    "qt": "TCP connections are not called Virtual connections.",
    "op": [
        "True",
        "False"
    ],
    "created_at": "2026-07-07T19:11:30.185594+00:00"
},
{
    "id": 57316,
    "cc": "CS610",
    "qn": "4",
    "dt": "08 July 2026",
    "qt": "_____ is less complex and easy to understand.",
    "op": [
        "UDP",
        "IP",
        "None of the given",
        "TCP"
    ],
    "created_at": "2026-07-07T19:11:41.683513+00:00"
},
{
    "id": 57320,
    "cc": "CS610",
    "qn": "4",
    "dt": "08 July 2026",
    "qt": "In 3-way handshake TCP requires to generate a random ________ sequence number.",
    "op": [
        "34 bit",
        "none of the given",
        "30 bit",
        "32 bit"
    ],
    "created_at": "2026-07-07T19:11:44.444968+00:00"
},
{
    "id": 57323,
    "cc": "CS610",
    "qn": "4",
    "dt": "08 July 2026",
    "qt": "The amount of buffer space available at any time is called the window.",
    "op": [
        "False",
        "True"
    ],
    "created_at": "2026-07-07T19:11:53.828558+00:00"
},
{
    "id": 57327,
    "cc": "CS610",
    "qn": "4",
    "dt": "08 July 2026",
    "qt": "________ field of header indicates whether a datagram is a fragment or a complete datagram.",
    "op": [
        "FLAGS",
        "IDENTIFICATION",
        "FRAGMENT OFFSET",
        "None of the given"
    ],
    "created_at": "2026-07-07T19:12:10.353757+00:00"
},
{
    "id": 57328,
    "cc": "CS610",
    "qn": "4",
    "dt": "08 July 2026",
    "qt": "The time for acknowledgement to arrive depends on __________",
    "op": [
        "Current traffic conditions",
        "Distance to destination",
        "none of the given",
        "Both a and b"
    ],
    "created_at": "2026-07-07T19:12:11.696556+00:00"
},
{
    "id": 57335,
    "cc": "CS610",
    "qn": "4",
    "dt": "08 July 2026",
    "qt": "TCP stands for _______",
    "op": [
        "none of the given",
        "Transport control protocol",
        "Transmission control protocol",
        "Terminal control protocol"
    ],
    "created_at": "2026-07-07T19:12:44.896599+00:00"
},
{
    "id": 57338,
    "cc": "CS610",
    "qn": "4",
    "dt": "08 July 2026",
    "qt": "_________ Serve Same purpose in Internet as frames on LAN",
    "op": [
        "Virtual Packets",
        "Both b and c",
        "Virtual Frames",
        "Packets"
    ],
    "created_at": "2026-07-07T19:12:48.941033+00:00"
},
{
    "id": 57357,
    "cc": "CS610",
    "qn": "4",
    "dt": "08 July 2026",
    "qt": "The Universal Datagram Protocol is a message-oriented protocol.",
    "op": [
        "True",
        "False"
    ],
    "created_at": "2026-07-07T19:14:30.364644+00:00"
},
{
    "id": 57382,
    "cc": "CS610",
    "qn": "4",
    "dt": "08 July 2026",
    "qt": "UDP follows four types of interactions.",
    "op": [
        "True",
        "False"
    ],
    "created_at": "2026-07-07T19:16:06.551153+00:00"
},
{
    "id": 57395,
    "cc": "CS610",
    "qn": "4",
    "dt": "08 July 2026",
    "qt": "IPV6 128 bits address includes network prefix and ________",
    "op": [
        "Source Prefix",
        "Host Suffix",
        "Host prefix",
        "none of the given"
    ],
    "created_at": "2026-07-07T19:16:39.31714+00:00"
},
{
    "id": 57405,
    "cc": "CS610",
    "qn": "4",
    "dt": "08 July 2026",
    "qt": "Which protocol is used to test different tools.",
    "op": [
        "IGMP",
        "TCP/IP",
        "none of the given",
        "ICMP"
    ],
    "created_at": "2026-07-07T19:17:14.032688+00:00"
},
{
    "id": 57409,
    "cc": "CS610",
    "qn": "4",
    "dt": "08 July 2026",
    "qt": "IP datagram can contains ________ octets.",
    "op": [
        "1-65,536",
        "0-65,535",
        "1-65,535",
        "none of the given"
    ],
    "created_at": "2026-07-07T19:17:34.526995+00:00"
},
{
    "id": 57426,
    "cc": "CS610",
    "qn": "4",
    "dt": "08 July 2026",
    "qt": "In Closed-form computation, the protocol address assigned to a computer is chosen carefully so that computer’s hardware address can be computed from the protocol address using basic Boolean and _________ operations.",
    "op": [
        "XNOR",
        "arithmetic",
        "XOR",
        "Shift"
    ],
    "created_at": "2026-07-07T19:19:05.522192+00:00"
},
{
    "id": 57432,
    "cc": "CS610",
    "qn": "4",
    "dt": "08 July 2026",
    "qt": "IPV6 addresses are _____ bits.",
    "op": [
        "32",
        "64",
        "256",
        "128"
    ],
    "created_at": "2026-07-07T19:20:07.771516+00:00"
},
{
    "id": 57435,
    "cc": "CS610",
    "qn": "4",
    "dt": "08 July 2026",
    "qt": "________ encapsulates IP datagram as data area in hardware frame.",
    "op": [
        "Datalink Layer",
        "Network Interface Layer",
        "None of the given",
        "Network Layer"
    ],
    "created_at": "2026-07-07T19:20:43.667822+00:00"
},
{
    "id": 57449,
    "cc": "CS610",
    "qn": "4",
    "dt": "08 July 2026",
    "qt": "End to End delivery Service of IP datagram is _____",
    "op": [
        "both a and b",
        "Connection oriented",
        "none of the given",
        "Connectionless"
    ],
    "created_at": "2026-07-07T19:22:10.252613+00:00"
},
{
    "id": 57450,
    "cc": "CS610",
    "qn": "4",
    "dt": "08 July 2026",
    "qt": "Mapping between a protocol address and a hardware address is called __________.",
    "op": [
        "Segmentation",
        "Hashing",
        "Fragmentation",
        "Address Resolution"
    ],
    "created_at": "2026-07-07T19:22:29.152778+00:00"
},
{
    "id": 57452,
    "cc": "CS610",
    "qn": "4",
    "dt": "08 July 2026",
    "qt": "In IPV6 the 128 bit addresses unwidely in dotted decimal;requires _____ numbers.",
    "op": [
        "12",
        "none of the given",
        "14",
        "16"
    ],
    "created_at": "2026-07-07T19:22:53.077684+00:00"
},
{
    "id": 57454,
    "cc": "CS610",
    "qn": "4",
    "dt": "08 July 2026",
    "qt": "TTL stands for __________",
    "op": [
        "Time to Leave",
        "Time to Learn",
        "none of the given",
        "Time to Live"
    ],
    "created_at": "2026-07-07T19:23:06.347009+00:00"
},
{
    "id": 57459,
    "cc": "CS610",
    "qn": "4",
    "dt": "08 July 2026",
    "qt": "The UDP stands for__________.",
    "op": [
        "United Datagram Protocol",
        "User Datagram Protocol",
        "Universal Datagram Protocol",
        "None of the given"
    ],
    "created_at": "2026-07-07T19:23:44.548205+00:00"
},
{
    "id": 57481,
    "cc": "CS610",
    "qn": "4",
    "dt": "08 July 2026",
    "qt": "Address Resolution Protocol is mostly used to bind a 32-bit IP address to a ____ Ethernet address.",
    "op": [
        "48-bit",
        "64-bit",
        "16-bit",
        "128-bit"
    ],
    "created_at": "2026-07-07T19:28:40.725232+00:00"
},
{
    "id": 57482,
    "cc": "CS610",
    "qn": "4",
    "dt": "08 July 2026",
    "qt": "H.LEN shows the header length in units of ____ Bits",
    "op": [
        "32",
        "34",
        "None of the given",
        "30"
    ],
    "created_at": "2026-07-07T19:28:54.176357+00:00"
},
{
    "id": 57487,
    "cc": "CS610",
    "qn": "4",
    "dt": "08 July 2026",
    "qt": "which is not the type of error messages defined by ICMP.",
    "op": [
        "none of the given",
        "Source quench",
        "Destination unreachable",
        "Time exceeded"
    ],
    "created_at": "2026-07-07T19:29:58.851523+00:00"
},
{
    "id": 57500,
    "cc": "CS610",
    "qn": "4",
    "dt": "08 July 2026",
    "qt": "IPV6 address with ______ leading zeros is interpreted to hold an IPV4 address.",
    "op": [
        "none of the given",
        "100",
        "96",
        "120"
    ],
    "created_at": "2026-07-07T19:32:37.076905+00:00"
},
{
    "id": 57501,
    "cc": "CS610",
    "qn": "4",
    "dt": "08 July 2026",
    "qt": "IPV6 address consists of ________",
    "op": [
        "128 Bits",
        "none of the given",
        "32 Bits",
        "64 Bits"
    ],
    "created_at": "2026-07-07T19:33:12.568093+00:00"
},
{
    "id": 57502,
    "cc": "CS610",
    "qn": "4",
    "dt": "08 July 2026",
    "qt": "_______ shows senders preference for low latency, high Reliability.",
    "op": [
        "None of the given",
        "TYPE",
        "SERVICE TYPE",
        "SERVICE PRIORITY"
    ],
    "created_at": "2026-07-07T19:33:29.138057+00:00"
},
{
    "id": 57506,
    "cc": "CS610",
    "qn": "4",
    "dt": "08 July 2026",
    "qt": "The Current version of IP-Version 4 is _____ old",
    "op": [
        "20 years",
        "22 years",
        "none of given",
        "18 years"
    ],
    "created_at": "2026-07-07T19:33:57.554017+00:00"
},
{
    "id": 57575,
    "cc": "CS610",
    "qn": "4",
    "dt": "08 July 2026",
    "qt": "In TCP/IP, ______ provides reliable transport service.",
    "op": [
        "IP",
        "Both IP and TCP",
        "None of the given",
        "TCP"
    ],
    "created_at": "2026-07-07T19:58:06.176862+00:00"
},
{
    "id": 57594,
    "cc": "CS610",
    "qn": "4",
    "dt": "08 July 2026",
    "qt": "TCP provides ________ communication.",
    "op": [
        "Full-duplex",
        "Half-duplex",
        "None of the given",
        "Both (a) and (b)"
    ],
    "created_at": "2026-07-07T20:16:12.069227+00:00"
},
{
    "id": 57599,
    "cc": "CS610",
    "qn": "4",
    "dt": "08 July 2026",
    "qt": "______ contains all information needed to deliver datagram to the destination.",
    "op": [
        "Header",
        "Data Area",
        "Identifier",
        "none of the given"
    ],
    "created_at": "2026-07-07T20:29:39.113082+00:00"
},
{
    "id": 57601,
    "cc": "CS610",
    "qn": "4",
    "dt": "08 July 2026",
    "qt": "One of the parameters, which motivated IP for change is address space. The _____________ address space allows for over a million networks.\nBut most networks are class C and too small for many organizations.",
    "op": [
        "16-bit",
        "64-bit",
        "128-bit",
        "32-bit"
    ],
    "created_at": "2026-07-07T20:32:33.28208+00:00"
},
{
    "id": 57605,
    "cc": "CS610",
    "qn": "4",
    "dt": "08 July 2026",
    "qt": "NEXT HEADER field in the base header defines type of header it appears at the end of fixed-size base header.",
    "op": [
        "True",
        "False"
    ],
    "created_at": "2026-07-07T20:48:30.137801+00:00"
},
{
    "id": 57755,
    "cc": "CS610",
    "qn": "4",
    "dt": "08 July 2026",
    "qt": "Due to revolutionalization of IP-V6 the speed has increased from _______",
    "op": [
        "512kbps to 1gbps",
        "none of the given",
        "56kbps to 1gbps",
        "56kbps to 512kbps"
    ],
    "created_at": "2026-07-08T02:03:01.598131+00:00"
},
{
    "id": 67079,
    "cc": "CS610",
    "qn": "3",
    "dt": "01 January 2026",
    "qt": "The Header format of IPv6 is entirely different.",
    "op": [
        "True",
        "False"
    ],
    "created_at": "2026-07-15T13:27:27.326546+00:00"
},
{
    "id": 67091,
    "cc": "CS610",
    "qn": "3",
    "dt": "01 January 2026",
    "qt": "Postfix defines how much of address used to identify network.",
    "op": [
        "True",
        "False"
    ],
    "created_at": "2026-07-15T13:27:27.326546+00:00"
},
{
    "id": 67189,
    "cc": "CS610",
    "qn": "3",
    "dt": "01 January 2026",
    "qt": "Address mask defines how many bits of address are in prefix.",
    "op": [
        "True",
        "False"
    ],
    "created_at": "2026-07-15T13:27:28.143271+00:00"
},
{
    "id": 71174,
    "cc": "CS610",
    "qn": "4",
    "dt": "08 January 2026",
    "qt": "The process of learning the path MTU is known as path MTU discovery.",
    "op": [
        "False",
        "True"
    ],
    "created_at": "2026-07-15T13:27:57.962061+00:00"
}
]