[
    {
        "id": 36455,
        "cc": "ZOO502",
        "qn": "02",
        "dt": "01 July 2026",
        "qt": "Hemoglobin is called oxyhemoglobin when _____________is bound.",
        "op": [
            "Potassium",
            "Carbon Dioxide",
            "Sodium",
            "Oxygen"
        ],
        "created_at": "2026-07-01T17:42:08.294049+00:00"
    },
    {
        "id": 36456,
        "cc": "ZOO502",
        "qn": "02",
        "dt": "01 July 2026",
        "qt": "The average total air holding lung capacity of an adult human Female is about _________of air.",
        "op": [
            "200 mL",
            "2300 mL",
            "4200 mL",
            "9000 mL"
        ],
        "created_at": "2026-07-01T17:42:25.260378+00:00"
    },
    {
        "id": 36457,
        "cc": "ZOO502",
        "qn": "02",
        "dt": "01 July 2026",
        "qt": "Serotonin is found in high concentration in the ____________ and blood platelets.",
        "op": [
            "Muscles",
            "Liver",
            "Head",
            "Gut"
        ],
        "created_at": "2026-07-01T17:42:36.765417+00:00"
    },
    {
        "id": 36458,
        "cc": "ZOO502",
        "qn": "02",
        "dt": "01 July 2026",
        "qt": "During Inspiration, the diaphragm_____________.",
        "op": [
            "Relaxes to become dome shaped",
            "Shows no change",
            "Expands",
            "Contracts"
        ],
        "created_at": "2026-07-01T17:43:06.999514+00:00"
    },
    {
        "id": 36460,
        "cc": "ZOO502",
        "qn": "02",
        "dt": "01 July 2026",
        "qt": "Amphibians, reptiles and mammals have ______________ baroreceptors in central Cardiovascular system.",
        "op": [
            "Myelinated",
            "Unmyelinated",
            "Myelinated, Unmyelinated",
            "Myelin sheath"
        ],
        "created_at": "2026-07-01T17:43:18.105658+00:00"
    },
    {
        "id": 36461,
        "cc": "ZOO502",
        "qn": "02",
        "dt": "01 July 2026",
        "qt": "Angiotensin II is produced  in______________.",
        "op": [
            "Liver",
            "Stomach",
            "Kidney",
            "Lungs"
        ],
        "created_at": "2026-07-01T17:43:51.195426+00:00"
    },
    {
        "id": 36462,
        "cc": "ZOO502",
        "qn": "02",
        "dt": "01 July 2026",
        "qt": "_____________is a potent vasoconstrictor hormone.",
        "op": [
            "Endothelin",
            "Prostacyclin",
            "Histamine",
            "Plasma kinins"
        ],
        "created_at": "2026-07-01T17:44:18.565232+00:00"
    },
    {
        "id": 36463,
        "cc": "ZOO502",
        "qn": "02",
        "dt": "01 July 2026",
        "qt": "A male human can forcefully expel additional ________air by use of accessory muscles.",
        "op": [
            "7000 mL",
            "9000 mL",
            "1000 mL",
            "10000 mL"
        ],
        "created_at": "2026-07-01T17:44:30.188399+00:00"
    }
]